OCP.cpython-311-darwin.so
cadquery_ocp_arm.dylibs/libGLEW.2.1.0.dylib
cadquery_ocp_arm.dylibs/libIex.31.3.2.2.dylib
cadquery_ocp_arm.dylibs/libIlmThread.31.3.2.2.dylib
cadquery_ocp_arm.dylibs/libImath.29.10.0.dylib
cadquery_ocp_arm.dylibs/libLerc.4.dylib
cadquery_ocp_arm.dylibs/libOpenEXR.31.3.2.2.dylib
cadquery_ocp_arm.dylibs/libOpenEXRCore.31.3.2.2.dylib
cadquery_ocp_arm.dylibs/libTKBO.7.7.2.dylib
cadquery_ocp_arm.dylibs/libTKBRep.7.7.2.dylib
cadquery_ocp_arm.dylibs/libTKBin.7.7.2.dylib
cadquery_ocp_arm.dylibs/libTKBinL.7.7.2.dylib
cadquery_ocp_arm.dylibs/libTKBinTObj.7.7.2.dylib
cadquery_ocp_arm.dylibs/libTKBinXCAF.7.7.2.dylib
cadquery_ocp_arm.dylibs/libTKBool.7.7.2.dylib
cadquery_ocp_arm.dylibs/libTKCAF.7.7.2.dylib
cadquery_ocp_arm.dylibs/libTKCDF.7.7.2.dylib
cadquery_ocp_arm.dylibs/libTKFeat.7.7.2.dylib
cadquery_ocp_arm.dylibs/libTKFillet.7.7.2.dylib
cadquery_ocp_arm.dylibs/libTKG2d.7.7.2.dylib
cadquery_ocp_arm.dylibs/libTKG3d.7.7.2.dylib
cadquery_ocp_arm.dylibs/libTKGeomAlgo.7.7.2.dylib
cadquery_ocp_arm.dylibs/libTKGeomBase.7.7.2.dylib
cadquery_ocp_arm.dylibs/libTKHLR.7.7.2.dylib
cadquery_ocp_arm.dylibs/libTKIGES.7.7.2.dylib
cadquery_ocp_arm.dylibs/libTKIVtk.7.7.2.dylib
cadquery_ocp_arm.dylibs/libTKLCAF.7.7.2.dylib
cadquery_ocp_arm.dylibs/libTKMath.7.7.2.dylib
cadquery_ocp_arm.dylibs/libTKMesh.7.7.2.dylib
cadquery_ocp_arm.dylibs/libTKMeshVS.7.7.2.dylib
cadquery_ocp_arm.dylibs/libTKOffset.7.7.2.dylib
cadquery_ocp_arm.dylibs/libTKOpenGl.7.7.2.dylib
cadquery_ocp_arm.dylibs/libTKPrim.7.7.2.dylib
cadquery_ocp_arm.dylibs/libTKRWMesh.7.7.2.dylib
cadquery_ocp_arm.dylibs/libTKSTEP.7.7.2.dylib
cadquery_ocp_arm.dylibs/libTKSTEP209.7.7.2.dylib
cadquery_ocp_arm.dylibs/libTKSTEPAttr.7.7.2.dylib
cadquery_ocp_arm.dylibs/libTKSTEPBase.7.7.2.dylib
cadquery_ocp_arm.dylibs/libTKSTL.7.7.2.dylib
cadquery_ocp_arm.dylibs/libTKService.7.7.2.dylib
cadquery_ocp_arm.dylibs/libTKShHealing.7.7.2.dylib
cadquery_ocp_arm.dylibs/libTKStd.7.7.2.dylib
cadquery_ocp_arm-7.7.2.1.dist-info/LICENSE
cadquery_ocp_arm-7.7.2.1.dist-info/LICENSES_bundled
cadquery_ocp_arm-7.7.2.1.dist-info/METADATA
cadquery_ocp_arm-7.7.2.1.dist-info/WHEEL
cadquery_ocp_arm-7.7.2.1.dist-info/dependency_links.txt
cadquery_ocp_arm-7.7.2.1.dist-info/top_level.txt
cadquery_ocp_arm-7.7.2.1.dist-info/RECORD
